ioos_tools/__init__.py
ioos_tools/_version.py
ioos_tools/ioos.py
ioos_tools/qaqc.py
ioos_tools/skill_score.py
ioos_tools/tardis.py
ioos_tools/taylor_diagram.py
ioos_tools-1.4.0.dist-info/LICENSE.txt
ioos_tools-1.4.0.dist-info/METADATA
ioos_tools-1.4.0.dist-info/WHEEL
ioos_tools-1.4.0.dist-info/top_level.txt
ioos_tools-1.4.0.dist-info/RECORD
