Metadata-Version: 2.1
Name: ioos-tools
Version: 1.4.0
Summary: Misc functions for IOOS notebooks
Home-page: https://github.com/pyoceans/ioos_tools/
Author: ['Rich Signell', 'Filipe Fernandes']
Author-email: ocefpaf@gmail.com
License: BSD-3-Clause
Keywords: oceanography,data analysis,IOOS
Platform: any
Classifier: Development Status :: 5 - Production/Stable
Classifier: Programming Language :: Python :: 3
Classifier: Programming Language :: Python :: 3.6
Classifier: Programming Language :: Python :: 3.7
Classifier: License :: OSI Approved :: BSD License
Classifier: Environment :: Console
Classifier: Intended Audience :: Science/Research
Classifier: Operating System :: OS Independent
Classifier: Topic :: Scientific/Engineering
Requires-Python: >=3.5
Requires-Dist: beautifulsoup4
Requires-Dist: cftime
Requires-Dist: folium
Requires-Dist: iris
Requires-Dist: jupyter
Requires-Dist: matplotlib
Requires-Dist: netcdf4
Requires-Dist: numpy
Requires-Dist: oceans
Requires-Dist: owslib
Requires-Dist: pandas (>=0.25.1)
Requires-Dist: pytz
Requires-Dist: requests
Requires-Dist: retrying
Requires-Dist: scikit-learn
Requires-Dist: scipy
Requires-Dist: timeout-decorator
Requires-Dist: lxml
Provides-Extra: testing
Requires-Dist: pytest ; extra == 'testing'
